<?xml version="1.0" encoding="utf-8" standalone="yes" ?>
<context_menu
 layout="topleft"
 name="Nearby People Context Menu">
    <menu_item_call
     label="View Profile"
     layout="topleft"
     name="view_profile">
        <menu_item_call.on_click
         function="Avatar.Profile" />
    </menu_item_call>
    <menu_item_call
     label="Add Friend"
     layout="topleft"
     name="add_friend">
        <menu_item_call.on_click
         function="Avatar.AddFriend" />
        <menu_item_call.on_visible
         function="Avatar.EnableItem"
         parameter="can_add" />
    </menu_item_call>
    <menu_item_call
     label="Remove Friend"
     layout="topleft"
     name="remove_friend">
        <menu_item_call.on_click
         function="Avatar.RemoveFriend" />
        <menu_item_call.on_visible
         function="Avatar.EnableItem"
         parameter="can_delete" />
    </menu_item_call>
    <menu_item_call
     label="Send IM"
     layout="topleft"
     name="im">
        <menu_item_call.on_click
         function="Avatar.IM" />
        <menu_item_call.on_enable
      	 function="Avatar.EnableItem"
         parameter="can_im"/> 
    </menu_item_call>
    <menu_item_call
    label="Offer Teleport"
    name="offer_teleport">
      <menu_item_call.on_click
       function="Avatar.OfferTeleport"/>
      <menu_item_call.on_enable
      function="Avatar.EnableItem"
      parameter="can_offer_teleport"/>
    </menu_item_call>
    <menu_item_call
    label="Request Teleport"
    name="request_teleport">
      <menu_item_call.on_click
       function="Avatar.TeleportRequest"/>
      <menu_item_call.on_enable
      function="Avatar.EnableItem"
      parameter="can_offer_teleport"/>
    </menu_item_call>
    <menu_item_call
     label="Voice call"
     layout="topleft"
     name="voice_call">
        <menu_item_call.on_click
         function="Avatar.Call" />
        <menu_item_call.on_enable
         function="Avatar.EnableItem"
         parameter="can_call" />
    </menu_item_call>
    <menu_item_call
     label="View chat history..."
     layout="topleft"
     name="chat_history">
        <menu_item_call.on_click
         function="Avatar.Calllog" />
        <menu_item_call.on_enable
      	 function="Avatar.EnableItem"
         parameter="can_callog"/>
    </menu_item_call>
    <menu_item_call
     label="Invite to group..."
     layout="topleft"
     name="invite_to_group">
        <menu_item_call.on_click
         function="Avatar.InviteToGroup" />
        <menu_item_call.on_enable
      	 function="Avatar.EnableItem"
         parameter="can_invite"/>
    </menu_item_call>

    <menu_item_separator name="clipboard_menu_separator" />

    <context_menu
        label="Copy To Clipboard"
        name="copy_to_clipboard">
        <menu_item_call
            label="Copy Avatar Name"
            name="copy_name">
            <menu_item_call.on_click
                function="Avatar.CopyName" />
        </menu_item_call>
        <menu_item_call
            label="Copy Avatar UUID"
            name="copy_uuid">
            <menu_item_call.on_click
                function="Avatar.CopyUUID" />
        </menu_item_call>
        <menu_item_call
            label="Copy Avatar Profile SLURL"
            name="copy_profile_slurl">
            <menu_item_call.on_click
                function="Avatar.CopyProfileSLURL" />
        </menu_item_call>
    </context_menu>

    <context_menu
        label="Permissions"
        name="permissions">
        <menu_item_check
            label="See when I am online"
            name="permission_online_status">
            <menu_item_check.on_click
                function="Avatar.ToggleRights"
                parameter="online_status" />
            <menu_item_check.on_check
                function="Avatar.CheckItem"
                parameter="online_status" />
            <menu_item_check.on_visible
                function="Avatar.EnableItem"
                parameter="can_delete" />
        </menu_item_check>
        <menu_item_check
            label="Find me on the world map"
            name="permission_map_location">
            <menu_item_check.on_click
                function="Avatar.ToggleRights"
                parameter="map_location" />
            <menu_item_check.on_check
                function="Avatar.CheckItem"
                parameter="map_location" />
            <menu_item_check.on_visible
                function="Avatar.EnableItem"
                parameter="can_delete" />
            <menu_item_check.on_enable
                function="Avatar.CheckItem"
                parameter="online_status" />
        </menu_item_check>
        <menu_item_check
            label="Edit, delete or take my objects"
            name="permission_modify_objects">
            <menu_item_check.on_click
                function="Avatar.ToggleRights"
                parameter="modify_objects" />
            <menu_item_check.on_check
                function="Avatar.CheckItem"
                parameter="modify_objects" />
            <menu_item_check.on_visible
                function="Avatar.EnableItem"
                parameter="can_delete" />
        </menu_item_check>
    </context_menu>

    <menu_item_separator name="separator_blockunblock"/>

    <menu_item_check
     label="Block"
     layout="topleft"
     name="block_unblock">
        <menu_item_check.on_click
         function="Avatar.BlockUnblock" />
        <menu_item_check.on_check
         function="Avatar.CheckItem"
         parameter="is_blocked" />
        <menu_item_check.on_enable
         function="Avatar.EnableItem"
         parameter="can_block" />
    </menu_item_check>
    <menu_item_call
     label="Zoom In"
     layout="topleft"
     name="zoom_in">
      <menu_item_call.on_click
       function="Avatar.ZoomIn" />
      <menu_item_call.on_enable
       function="Avatar.EnableItem"
       parameter="can_zoom_in"/>
    </menu_item_call>
    <menu_item_call
     label="Show on Map"
     layout="topleft"
     name="map">
        <menu_item_call.on_click
         function="Avatar.ShowOnMap" />
        <menu_item_call.on_enable
         function="Avatar.EnableItem"
         parameter="can_show_on_map" />
    </menu_item_call>
    <menu_item_call
     label="Share"
     layout="topleft"
     name="share">
        <menu_item_call.on_click
         function="Avatar.Share" />
        <menu_item_call.on_enable
      	 function="Avatar.EnableItem"
         parameter="can_share"/>
    </menu_item_call>
    <menu_item_call
     label="Pay"
     layout="topleft"
     name="pay">
        <menu_item_call.on_click
         function="Avatar.Pay" />
        <menu_item_call.on_enable
      	 function="Avatar.EnableItem"
         parameter="can_pay"/> 
    </menu_item_call>
    <menu_item_separator name="separator_freeze_eject" />
    <menu_item_call
     label="Freeze / Unfreeze"
     layout="topleft"
     name="freeze">
        <menu_item_call.on_click
         function="Avatar.Freeze" />
    </menu_item_call>
    <menu_item_call
     label="Eject / Ban"
     layout="topleft"
     name="eject">
        <menu_item_call.on_click
         function="Avatar.Eject" />
    </menu_item_call>
    <menu_item_call
     label="Teleport Home"
     layout="topleft"
     name="teleport_home">
        <menu_item_call.on_click
         function="Avatar.TeleportHome" />
    </menu_item_call>
    <menu_item_call
     label="Estate Ban"
     layout="topleft"
     name="estate_ban">
        <menu_item_call.on_click
         function="Avatar.EstateBan" />
    </menu_item_call>
</context_menu>
